README.md
setup.cfg
setup.py
kfjsonfilter/__init__.py
kfjsonfilter/jsonFieldFilter.py
kfjsonfilter/jsonFieldSearchFilter.py
kfjsonfilter/utils.py
kfjsonfilter.egg-info/PKG-INFO
kfjsonfilter.egg-info/SOURCES.txt
kfjsonfilter.egg-info/dependency_links.txt
kfjsonfilter.egg-info/not-zip-safe
kfjsonfilter.egg-info/requires.txt
kfjsonfilter.egg-info/top_level.txt