Metadata-Version: 2.1
Name: kfjsonfilter
Version: 0.1
Summary: Json Data Filter for django and django rest framework
Home-page: https://gitlab.com/kas-factory/packages/drf-json-filter
Author: Aurora @ KF
Author-email: aurora@kasfactory.net
License: COPYRIGHT
Platform: UNKNOWN
